README.md
pony_rest.py
setup.py
pony_rest.egg-info/PKG-INFO
pony_rest.egg-info/SOURCES.txt
pony_rest.egg-info/dependency_links.txt
pony_rest.egg-info/requires.txt
pony_rest.egg-info/top_level.txt