Metadata-Version: 2.1
Name: pony-rest
Version: 2.3
Summary: Restful API generated by ponyorm and tornado
Home-page: https://github.com/lwzm/pony-rest
Author: lwzm
Author-email: lwzm@qq.com
License: UNKNOWN
Keywords: rest,restful,pony,tornado,http,api
Platform: UNKNOWN
Classifier: Environment :: Console
Classifier: Programming Language :: Python :: 3
Classifier: Programming Language :: Python :: 3.5
Classifier: Programming Language :: Python :: 3.6
Classifier: Programming Language :: Python :: 3.7
Classifier: Programming Language :: Python :: Implementation :: CPython
Classifier: Programming Language :: Python :: Implementation :: PyPy
Classifier: Topic :: Software Development :: Build Tools
Classifier: Topic :: Software Development :: Libraries :: Python Modules
Classifier: License :: OSI Approved :: MIT License
